{"method": "GET", "path": "/", "endpoint": "start_page.start_page", "view-args": {}, "status": 302, "user": "alexandra.deichsel@project-a.com", "timestamp": "2018-11-07T14:15:57.733818", "browser": "chrome", "browser-platform": "macos", "browser-version": "68.0.3440.106"}
{"method": "GET", "path": "/dashboards/marketing-overview", "endpoint": "dashboards.view_dashboard", "view-args": {"id": "marketing-overview"}, "status": 200, "user": "alexandra.deichsel@project-a.com", "timestamp": "2018-11-07T14:15:57.958729", "browser": "chrome", "browser-platform": "macos", "browser-version": "68.0.3440.106"}
{"method": "GET", "path": "/dashboards/_render_async_sql_query/c049356b-9270-4ec2-b06b-0fb2b4d6bdf2", "endpoint": "dashboards.render_async_sql_query", "view-args": {"id": "c049356b-9270-4ec2-b06b-0fb2b4d6bdf2"}, "status": 200, "user": "alexandra.deichsel@project-a.com", "timestamp": "2018-11-07T14:15:59.179544", "browser": "chrome", "browser-platform": "macos", "browser-version": "68.0.3440.106"}
{"method": "GET", "path": "/dashboards/_render_async_sql_query/e889c904-7251-4723-9a9b-c0920df4bf6a", "endpoint": "dashboards.render_async_sql_query", "view-args": {"id": "e889c904-7251-4723-9a9b-c0920df4bf6a"}, "status": 200, "user": "alexandra.deichsel@project-a.com", "timestamp": "2018-11-07T14:15:59.183976", "browser": "chrome", "browser-platform": "macos", "browser-version": "68.0.3440.106"}
{"method": "GET", "path": "/dashboards/_render_async_sql_query/e36ddf36-5be8-4325-ae75-26845b7aacf0", "endpoint": "dashboards.render_async_sql_query", "view-args": {"id": "e36ddf36-5be8-4325-ae75-26845b7aacf0"}, "status": 200, "user": "alexandra.deichsel@project-a.com", "timestamp": "2018-11-07T14:15:59.188324", "browser": "chrome", "browser-platform": "macos", "browser-version": "68.0.3440.106"}
{"method": "GET", "path": "/dashboards/_last_successful_import", "endpoint": "dashboards.last_successful_import", "view-args": {}, "status": 200, "user": "alexandra.deichsel@project-a.com", "timestamp": "2018-11-07T14:15:59.202553", "browser": "chrome", "browser-platform": "macos", "browser-version": "68.0.3440.106"}
{"method": "GET", "path": "/dashboards/_render_async_sql_query/d905454b-4d72-40bf-b9cd-06fe2e8990cb", "endpoint": "dashboards.render_async_sql_query", "view-args": {"id": "d905454b-4d72-40bf-b9cd-06fe2e8990cb"}, "status": 200, "user": "alexandra.deichsel@project-a.com", "timestamp": "2018-11-07T14:15:59.206133", "browser": "chrome", "browser-platform": "macos", "browser-version": "68.0.3440.106"}
{"method": "GET", "path": "/dashboards/_render_async_sql_query/997e43e6-a529-4426-8d71-268190e7e3c6", "endpoint": "dashboards.render_async_sql_query", "view-args": {"id": "997e43e6-a529-4426-8d71-268190e7e3c6"}, "status": 200, "user": "alexandra.deichsel@project-a.com", "timestamp": "2018-11-07T14:15:59.285193", "browser": "chrome", "browser-platform": "macos", "browser-version": "68.0.3440.106"}
{"method": "GET", "path": "/dashboards/_render_async_sql_query/377dfca6-d9f7-4734-9f31-91bc0793443c", "endpoint": "dashboards.render_async_sql_query", "view-args": {"id": "377dfca6-d9f7-4734-9f31-91bc0793443c"}, "status": 200, "user": "alexandra.deichsel@project-a.com", "timestamp": "2018-11-07T14:15:59.285445", "browser": "chrome", "browser-platform": "macos", "browser-version": "68.0.3440.106"}
{"method": "GET", "path": "/dashboards/_render_async_sql_query/8b678907-393a-43f2-bcf0-80cf033450aa", "endpoint": "dashboards.render_async_sql_query", "view-args": {"id": "8b678907-393a-43f2-bcf0-80cf033450aa"}, "status": 200, "user": "alexandra.deichsel@project-a.com", "timestamp": "2018-11-07T14:15:59.300877", "browser": "chrome", "browser-platform": "macos", "browser-version": "68.0.3440.106"}
{"method": "GET", "path": "/dashboards/_render_async_sql_query/a0c3710e-ae74-40f6-9b21-46c543629df1", "endpoint": "dashboards.render_async_sql_query", "view-args": {"id": "a0c3710e-ae74-40f6-9b21-46c543629df1"}, "status": 200, "user": "alexandra.deichsel@project-a.com", "timestamp": "2018-11-07T14:15:59.306552", "browser": "chrome", "browser-platform": "macos", "browser-version": "68.0.3440.106"}
{"method": "GET", "path": "/dashboards/_render_async_sql_query/ff2fb302-f31f-47b8-88af-3d13aa8e53de", "endpoint": "dashboards.render_async_sql_query", "view-args": {"id": "ff2fb302-f31f-47b8-88af-3d13aa8e53de"}, "status": 200, "user": "alexandra.deichsel@project-a.com", "timestamp": "2018-11-07T14:15:59.575675", "browser": "chrome", "browser-platform": "macos", "browser-version": "68.0.3440.106"}
{"method": "GET", "path": "/dashboards/_render_async_sql_query/6eb514f6-7a7d-43f0-80cf-510e1aa92663", "endpoint": "dashboards.render_async_sql_query", "view-args": {"id": "6eb514f6-7a7d-43f0-80cf-510e1aa92663"}, "status": 200, "user": "alexandra.deichsel@project-a.com", "timestamp": "2018-11-07T14:15:59.582401", "browser": "chrome", "browser-platform": "macos", "browser-version": "68.0.3440.106"}
{"method": "GET", "path": "/dashboards/_render_async_sql_query/f362beb3-18ad-45f3-9913-15cbc4572d41", "endpoint": "dashboards.render_async_sql_query", "view-args": {"id": "f362beb3-18ad-45f3-9913-15cbc4572d41"}, "status": 200, "user": "alexandra.deichsel@project-a.com", "timestamp": "2018-11-07T14:15:59.587443", "browser": "chrome", "browser-platform": "macos", "browser-version": "68.0.3440.106"}
{"method": "GET", "path": "/dashboards/_render_async_sql_query/268d63cc-00a2-4933-9199-c35ec21b3efb", "endpoint": "dashboards.render_async_sql_query", "view-args": {"id": "268d63cc-00a2-4933-9199-c35ec21b3efb"}, "status": 200, "user": "alexandra.deichsel@project-a.com", "timestamp": "2018-11-07T14:15:59.599743", "browser": "chrome", "browser-platform": "macos", "browser-version": "68.0.3440.106"}
{"method": "GET", "path": "/dashboards/_render_async_sql_query/1eaad8b9-f01b-4ad3-8c01-a988d9845a8f", "endpoint": "dashboards.render_async_sql_query", "view-args": {"id": "1eaad8b9-f01b-4ad3-8c01-a988d9845a8f"}, "status": 200, "user": "alexandra.deichsel@project-a.com", "timestamp": "2018-11-07T14:15:59.821563", "browser": "chrome", "browser-platform": "macos", "browser-version": "68.0.3440.106"}
{"method": "GET", "path": "/dashboards/_render_async_sql_query/949c3a64-437b-43cc-923e-908e11236b98", "endpoint": "dashboards.render_async_sql_query", "view-args": {"id": "949c3a64-437b-43cc-923e-908e11236b98"}, "status": 200, "user": "alexandra.deichsel@project-a.com", "timestamp": "2018-11-07T14:15:59.823188", "browser": "chrome", "browser-platform": "macos", "browser-version": "68.0.3440.106"}
{"method": "GET", "path": "/dashboards/_render_async_sql_query/29145885-76cb-42aa-b437-7d545091f939", "endpoint": "dashboards.render_async_sql_query", "view-args": {"id": "29145885-76cb-42aa-b437-7d545091f939"}, "status": 200, "user": "alexandra.deichsel@project-a.com", "timestamp": "2018-11-07T14:15:59.824708", "browser": "chrome", "browser-platform": "macos", "browser-version": "68.0.3440.106"}
{"method": "GET", "path": "/dashboards/_render_async_sql_query/572d1025-9ae8-4572-ad1c-8ce5021e60f1", "endpoint": "dashboards.render_async_sql_query", "view-args": {"id": "572d1025-9ae8-4572-ad1c-8ce5021e60f1"}, "status": 200, "user": "alexandra.deichsel@project-a.com", "timestamp": "2018-11-07T14:15:59.843382", "browser": "chrome", "browser-platform": "macos", "browser-version": "68.0.3440.106"}
{"method": "GET", "path": "/mondrian/saiku", "endpoint": "py_mondrian.saiku", "view-args": {}, "status": 302, "user": "alexandra.deichsel@project-a.com", "timestamp": "2018-11-07T14:18:25.454653", "browser": "chrome", "browser-platform": "macos", "browser-version": "68.0.3440.106"}
{"method": "POST", "path": "/mondrian/saiku/authorize", "endpoint": "py_mondrian.saiku_authorize", "view-args": {}, "status": 200, "user": "guest@localhost", "timestamp": "2018-11-07T14:18:26.294493", "browser": null, "browser-platform": null, "browser-version": null}
{"method": "POST", "path": "/mondrian/saiku/authorize", "endpoint": "py_mondrian.saiku_authorize", "view-args": {}, "status": 200, "user": "guest@localhost", "timestamp": "2018-11-07T14:18:26.309821", "browser": null, "browser-platform": null, "browser-version": null}
{"method": "GET", "path": "/", "endpoint": "start_page.start_page", "view-args": {}, "status": 302, "user": "martin.loetzsch@project-a.com", "timestamp": "2018-11-07T14:24:58.965889", "browser": "chrome", "browser-platform": "macos", "browser-version": "70.0.3538.77"}
{"method": "GET", "path": "/dashboards/marketing-overview", "endpoint": "dashboards.view_dashboard", "view-args": {"id": "marketing-overview"}, "status": 200, "user": "martin.loetzsch@project-a.com", "timestamp": "2018-11-07T14:24:59.180084", "browser": "chrome", "browser-platform": "macos", "browser-version": "70.0.3538.77"}
{"method": "GET", "path": "/", "endpoint": "start_page.start_page", "view-args": {}, "status": 302, "user": "martin.loetzsch@project-a.com", "timestamp": "2018-11-07T14:24:59.634744", "browser": "chrome", "browser-platform": "macos", "browser-version": "70.0.3538.77"}
{"method": "GET", "path": "/dashboards/marketing-overview", "endpoint": "dashboards.view_dashboard", "view-args": {"id": "marketing-overview"}, "status": 200, "user": "martin.loetzsch@project-a.com", "timestamp": "2018-11-07T14:24:59.860101", "browser": "chrome", "browser-platform": "macos", "browser-version": "70.0.3538.77"}
{"method": "GET", "path": "/dashboards/_render_async_sql_query/b5ffc171-3019-4b46-8bf8-9db240278c01", "endpoint": "dashboards.render_async_sql_query", "view-args": {"id": "b5ffc171-3019-4b46-8bf8-9db240278c01"}, "status": 200, "user": "martin.loetzsch@project-a.com", "timestamp": "2018-11-07T14:25:00.700541", "browser": "chrome", "browser-platform": "macos", "browser-version": "70.0.3538.77"}
{"method": "GET", "path": "/dashboards/_render_async_sql_query/d1c36162-879a-4688-95db-8fee6bd615f4", "endpoint": "dashboards.render_async_sql_query", "view-args": {"id": "d1c36162-879a-4688-95db-8fee6bd615f4"}, "status": 200, "user": "martin.loetzsch@project-a.com", "timestamp": "2018-11-07T14:25:00.704836", "browser": "chrome", "browser-platform": "macos", "browser-version": "70.0.3538.77"}
{"method": "GET", "path": "/dashboards/_render_async_sql_query/51c75f72-b332-4042-8466-12e7166c24c4", "endpoint": "dashboards.render_async_sql_query", "view-args": {"id": "51c75f72-b332-4042-8466-12e7166c24c4"}, "status": 200, "user": "martin.loetzsch@project-a.com", "timestamp": "2018-11-07T14:25:00.705369", "browser": "chrome", "browser-platform": "macos", "browser-version": "70.0.3538.77"}
{"method": "GET", "path": "/dashboards/_last_successful_import", "endpoint": "dashboards.last_successful_import", "view-args": {}, "status": 200, "user": "martin.loetzsch@project-a.com", "timestamp": "2018-11-07T14:25:00.719717", "browser": "chrome", "browser-platform": "macos", "browser-version": "70.0.3538.77"}
{"method": "GET", "path": "/dashboards/_render_async_sql_query/8b5a73dc-4745-4d32-90c1-4087b5fcebc6", "endpoint": "dashboards.render_async_sql_query", "view-args": {"id": "8b5a73dc-4745-4d32-90c1-4087b5fcebc6"}, "status": 200, "user": "martin.loetzsch@project-a.com", "timestamp": "2018-11-07T14:25:00.729936", "browser": "chrome", "browser-platform": "macos", "browser-version": "70.0.3538.77"}
{"method": "GET", "path": "/dashboards/_render_async_sql_query/21db11b1-2660-49bf-a0f9-3b3a5d5bede2", "endpoint": "dashboards.render_async_sql_query", "view-args": {"id": "21db11b1-2660-49bf-a0f9-3b3a5d5bede2"}, "status": 200, "user": "martin.loetzsch@project-a.com", "timestamp": "2018-11-07T14:25:00.804045", "browser": "chrome", "browser-platform": "macos", "browser-version": "70.0.3538.77"}
{"method": "GET", "path": "/dashboards/_render_async_sql_query/dc5771fb-aee5-498c-aeb4-a636137c8be3", "endpoint": "dashboards.render_async_sql_query", "view-args": {"id": "dc5771fb-aee5-498c-aeb4-a636137c8be3"}, "status": 200, "user": "martin.loetzsch@project-a.com", "timestamp": "2018-11-07T14:25:00.815160", "browser": "chrome", "browser-platform": "macos", "browser-version": "70.0.3538.77"}
{"method": "GET", "path": "/dashboards/_render_async_sql_query/5e60423d-b275-4fb6-bedd-40666a92bca2", "endpoint": "dashboards.render_async_sql_query", "view-args": {"id": "5e60423d-b275-4fb6-bedd-40666a92bca2"}, "status": 200, "user": "martin.loetzsch@project-a.com", "timestamp": "2018-11-07T14:25:00.821641", "browser": "chrome", "browser-platform": "macos", "browser-version": "70.0.3538.77"}
{"method": "GET", "path": "/dashboards/_render_async_sql_query/b9da549d-ebdc-41b6-ac1f-633097936318", "endpoint": "dashboards.render_async_sql_query", "view-args": {"id": "b9da549d-ebdc-41b6-ac1f-633097936318"}, "status": 200, "user": "martin.loetzsch@project-a.com", "timestamp": "2018-11-07T14:25:00.827417", "browser": "chrome", "browser-platform": "macos", "browser-version": "70.0.3538.77"}
{"method": "GET", "path": "/dashboards/_render_async_sql_query/30188572-caee-4c9f-bbe8-cc1034e28cd7", "endpoint": "dashboards.render_async_sql_query", "view-args": {"id": "30188572-caee-4c9f-bbe8-cc1034e28cd7"}, "status": 200, "user": "martin.loetzsch@project-a.com", "timestamp": "2018-11-07T14:25:01.048237", "browser": "chrome", "browser-platform": "macos", "browser-version": "70.0.3538.77"}
{"method": "GET", "path": "/dashboards/_render_async_sql_query/9fa39420-5684-422d-92e0-be3c306f4d8d", "endpoint": "dashboards.render_async_sql_query", "view-args": {"id": "9fa39420-5684-422d-92e0-be3c306f4d8d"}, "status": 200, "user": "martin.loetzsch@project-a.com", "timestamp": "2018-11-07T14:25:01.048968", "browser": "chrome", "browser-platform": "macos", "browser-version": "70.0.3538.77"}
{"method": "GET", "path": "/dashboards/_render_async_sql_query/9e311897-0160-40c6-a407-dbf4b56e1975", "endpoint": "dashboards.render_async_sql_query", "view-args": {"id": "9e311897-0160-40c6-a407-dbf4b56e1975"}, "status": 200, "user": "martin.loetzsch@project-a.com", "timestamp": "2018-11-07T14:25:01.057103", "browser": "chrome", "browser-platform": "macos", "browser-version": "70.0.3538.77"}
{"method": "GET", "path": "/dashboards/_render_async_sql_query/a422dd7d-d05d-4943-963f-fab334767189", "endpoint": "dashboards.render_async_sql_query", "view-args": {"id": "a422dd7d-d05d-4943-963f-fab334767189"}, "status": 200, "user": "martin.loetzsch@project-a.com", "timestamp": "2018-11-07T14:25:01.072224", "browser": "chrome", "browser-platform": "macos", "browser-version": "70.0.3538.77"}
{"method": "GET", "path": "/dashboards/_render_async_sql_query/efc4d453-1355-4e4f-91d5-3c524a6ec611", "endpoint": "dashboards.render_async_sql_query", "view-args": {"id": "efc4d453-1355-4e4f-91d5-3c524a6ec611"}, "status": 200, "user": "martin.loetzsch@project-a.com", "timestamp": "2018-11-07T14:25:01.384011", "browser": "chrome", "browser-platform": "macos", "browser-version": "70.0.3538.77"}
{"method": "GET", "path": "/dashboards/_render_async_sql_query/397509ff-1b82-44fa-a1c8-2d1941c7aeae", "endpoint": "dashboards.render_async_sql_query", "view-args": {"id": "397509ff-1b82-44fa-a1c8-2d1941c7aeae"}, "status": 200, "user": "martin.loetzsch@project-a.com", "timestamp": "2018-11-07T14:25:01.423470", "browser": "chrome", "browser-platform": "macos", "browser-version": "70.0.3538.77"}
{"method": "GET", "path": "/dashboards/_render_async_sql_query/d49f877f-ffc3-40a0-a9d5-ecfa7417d3fe", "endpoint": "dashboards.render_async_sql_query", "view-args": {"id": "d49f877f-ffc3-40a0-a9d5-ecfa7417d3fe"}, "status": 200, "user": "martin.loetzsch@project-a.com", "timestamp": "2018-11-07T14:25:01.448641", "browser": "chrome", "browser-platform": "macos", "browser-version": "70.0.3538.77"}
{"method": "GET", "path": "/dashboards/_render_async_sql_query/0b86822f-dee6-46cb-8397-840ac5a6ffd2", "endpoint": "dashboards.render_async_sql_query", "view-args": {"id": "0b86822f-dee6-46cb-8397-840ac5a6ffd2"}, "status": 200, "user": "martin.loetzsch@project-a.com", "timestamp": "2018-11-07T14:25:01.469986", "browser": "chrome", "browser-platform": "macos", "browser-version": "70.0.3538.77"}
{"method": "GET", "path": "/mondrian", "endpoint": "py_mondrian.schema_page", "view-args": {}, "status": 200, "user": "martin.loetzsch@project-a.com", "timestamp": "2018-11-07T14:25:07.684897", "browser": "chrome", "browser-platform": "macos", "browser-version": "70.0.3538.77"}
{"method": "GET", "path": "/mondrian/graph/Business targets", "endpoint": "py_mondrian.measures_graph", "view-args": {"cube_name": "Business targets"}, "status": 200, "user": "martin.loetzsch@project-a.com", "timestamp": "2018-11-07T14:25:08.223627", "browser": "chrome", "browser-platform": "macos", "browser-version": "70.0.3538.77"}
{"method": "GET", "path": "/mondrian/graph/Database size", "endpoint": "py_mondrian.measures_graph", "view-args": {"cube_name": "Database size"}, "status": 200, "user": "martin.loetzsch@project-a.com", "timestamp": "2018-11-07T14:25:08.223864", "browser": "chrome", "browser-platform": "macos", "browser-version": "70.0.3538.77"}
{"method": "GET", "path": "/mondrian/graph/Ad performance", "endpoint": "py_mondrian.measures_graph", "view-args": {"cube_name": "Ad performance"}, "status": 200, "user": "martin.loetzsch@project-a.com", "timestamp": "2018-11-07T14:25:08.226727", "browser": "chrome", "browser-platform": "macos", "browser-version": "70.0.3538.77"}
{"method": "GET", "path": "/mondrian/graph/Marketing cost", "endpoint": "py_mondrian.measures_graph", "view-args": {"cube_name": "Marketing cost"}, "status": 200, "user": "martin.loetzsch@project-a.com", "timestamp": "2018-11-07T14:25:08.257171", "browser": "chrome", "browser-platform": "macos", "browser-version": "70.0.3538.77"}
{"method": "GET", "path": "/mondrian/graph/Marketing touchpoints", "endpoint": "py_mondrian.measures_graph", "view-args": {"cube_name": "Marketing touchpoints"}, "status": 200, "user": "martin.loetzsch@project-a.com", "timestamp": "2018-11-07T14:25:08.262764", "browser": "chrome", "browser-platform": "macos", "browser-version": "70.0.3538.77"}
{"method": "GET", "path": "/mondrian/graph/Email performance", "endpoint": "py_mondrian.measures_graph", "view-args": {"cube_name": "Email performance"}, "status": 200, "user": "martin.loetzsch@project-a.com", "timestamp": "2018-11-07T14:25:08.265845", "browser": "chrome", "browser-platform": "macos", "browser-version": "70.0.3538.77"}
{"method": "GET", "path": "/mondrian/graph/User stats", "endpoint": "py_mondrian.measures_graph", "view-args": {"cube_name": "User stats"}, "status": 200, "user": "martin.loetzsch@project-a.com", "timestamp": "2018-11-07T14:25:08.300512", "browser": "chrome", "browser-platform": "macos", "browser-version": "70.0.3538.77"}
{"method": "GET", "path": "/mondrian/graph/Merged Customers", "endpoint": "py_mondrian.measures_graph", "view-args": {"cube_name": "Merged Customers"}, "status": 200, "user": "martin.loetzsch@project-a.com", "timestamp": "2018-11-07T14:25:08.303150", "browser": "chrome", "browser-platform": "macos", "browser-version": "70.0.3538.77"}
{"method": "GET", "path": "/mondrian/graph/Order items", "endpoint": "py_mondrian.measures_graph", "view-args": {"cube_name": "Order items"}, "status": 200, "user": "martin.loetzsch@project-a.com", "timestamp": "2018-11-07T14:25:08.312306", "browser": "chrome", "browser-platform": "macos", "browser-version": "70.0.3538.77"}
{"method": "GET", "path": "/mondrian/graph/Webshop performance", "endpoint": "py_mondrian.measures_graph", "view-args": {"cube_name": "Webshop performance"}, "status": 200, "user": "martin.loetzsch@project-a.com", "timestamp": "2018-11-07T14:25:08.334873", "browser": "chrome", "browser-platform": "macos", "browser-version": "70.0.3538.77"}
{"method": "GET", "path": "/mondrian/saiku", "endpoint": "py_mondrian.saiku", "view-args": {}, "status": 302, "user": "martin.loetzsch@project-a.com", "timestamp": "2018-11-07T14:29:12.107949", "browser": "chrome", "browser-platform": "macos", "browser-version": "70.0.3538.77"}
{"method": "POST", "path": "/mondrian/saiku/authorize", "endpoint": "py_mondrian.saiku_authorize", "view-args": {}, "status": 200, "user": "guest@localhost", "timestamp": "2018-11-07T14:29:12.201637", "browser": null, "browser-platform": null, "browser-version": null}
{"method": "POST", "path": "/mondrian/saiku/authorize", "endpoint": "py_mondrian.saiku_authorize", "view-args": {}, "status": 200, "user": "guest@localhost", "timestamp": "2018-11-07T14:29:13.101019", "browser": null, "browser-platform": null, "browser-version": null}
{"method": "POST", "path": "/dashboards/shop-performance-overview", "endpoint": "dashboards.view_dashboard", "view-args": {"id": "shop-performance-overview"}, "status": 200, "user": "felix.pittorf@lampenwelt.de", "timestamp": "2018-11-07T14:55:20.161977", "browser": "chrome", "browser-platform": "windows", "browser-version": "70.0.3538.77"}
{"method": "GET", "path": "/dashboards/_render_async_sql_query/d58c84e3-8f8e-4ebb-b30c-69456a83edb5", "endpoint": "dashboards.render_async_sql_query", "view-args": {"id": "d58c84e3-8f8e-4ebb-b30c-69456a83edb5"}, "status": 200, "user": "felix.pittorf@lampenwelt.de", "timestamp": "2018-11-07T14:55:20.978324", "browser": "chrome", "browser-platform": "windows", "browser-version": "70.0.3538.77"}
{"method": "GET", "path": "/dashboards/_render_async_sql_query/3bd57d2a-07fe-47f6-9aa0-8f58800e14e2", "endpoint": "dashboards.render_async_sql_query", "view-args": {"id": "3bd57d2a-07fe-47f6-9aa0-8f58800e14e2"}, "status": 200, "user": "felix.pittorf@lampenwelt.de", "timestamp": "2018-11-07T14:55:20.988206", "browser": "chrome", "browser-platform": "windows", "browser-version": "70.0.3538.77"}
{"method": "GET", "path": "/dashboards/_render_async_sql_query/70126175-173c-431f-82e5-b301d2bbcd10", "endpoint": "dashboards.render_async_sql_query", "view-args": {"id": "70126175-173c-431f-82e5-b301d2bbcd10"}, "status": 200, "user": "felix.pittorf@lampenwelt.de", "timestamp": "2018-11-07T14:55:20.991154", "browser": "chrome", "browser-platform": "windows", "browser-version": "70.0.3538.77"}
{"method": "GET", "path": "/dashboards/_last_successful_import", "endpoint": "dashboards.last_successful_import", "view-args": {}, "status": 200, "user": "felix.pittorf@lampenwelt.de", "timestamp": "2018-11-07T14:55:21.005986", "browser": "chrome", "browser-platform": "windows", "browser-version": "70.0.3538.77"}
{"method": "GET", "path": "/dashboards/_render_async_sql_query/846f0bdc-f8eb-4511-97d0-5a678c077f93", "endpoint": "dashboards.render_async_sql_query", "view-args": {"id": "846f0bdc-f8eb-4511-97d0-5a678c077f93"}, "status": 200, "user": "felix.pittorf@lampenwelt.de", "timestamp": "2018-11-07T14:55:21.099480", "browser": "chrome", "browser-platform": "windows", "browser-version": "70.0.3538.77"}
{"method": "GET", "path": "/dashboards/_render_async_sql_query/522b6310-bb4f-4604-8a8b-facb08f73527", "endpoint": "dashboards.render_async_sql_query", "view-args": {"id": "522b6310-bb4f-4604-8a8b-facb08f73527"}, "status": 200, "user": "felix.pittorf@lampenwelt.de", "timestamp": "2018-11-07T14:55:21.167160", "browser": "chrome", "browser-platform": "windows", "browser-version": "70.0.3538.77"}
{"method": "GET", "path": "/dashboards/_render_async_sql_query/ecdec4af-1918-4244-a09c-564ea86fe71d", "endpoint": "dashboards.render_async_sql_query", "view-args": {"id": "ecdec4af-1918-4244-a09c-564ea86fe71d"}, "status": 200, "user": "felix.pittorf@lampenwelt.de", "timestamp": "2018-11-07T14:55:21.170311", "browser": "chrome", "browser-platform": "windows", "browser-version": "70.0.3538.77"}
{"method": "GET", "path": "/dashboards/_render_async_sql_query/b9e2b022-9579-453f-9e3f-dc3afd479cae", "endpoint": "dashboards.render_async_sql_query", "view-args": {"id": "b9e2b022-9579-453f-9e3f-dc3afd479cae"}, "status": 200, "user": "felix.pittorf@lampenwelt.de", "timestamp": "2018-11-07T14:55:21.217969", "browser": "chrome", "browser-platform": "windows", "browser-version": "70.0.3538.77"}
{"method": "GET", "path": "/dashboards/_render_async_sql_query/4221d4c9-062c-4321-bcdd-b6a2f1017557", "endpoint": "dashboards.render_async_sql_query", "view-args": {"id": "4221d4c9-062c-4321-bcdd-b6a2f1017557"}, "status": 200, "user": "felix.pittorf@lampenwelt.de", "timestamp": "2018-11-07T14:55:21.353831", "browser": "chrome", "browser-platform": "windows", "browser-version": "70.0.3538.77"}
{"method": "GET", "path": "/dashboards/_render_async_sql_query/e47dc302-8d61-405e-a318-c4cb94d8d4f8", "endpoint": "dashboards.render_async_sql_query", "view-args": {"id": "e47dc302-8d61-405e-a318-c4cb94d8d4f8"}, "status": 200, "user": "felix.pittorf@lampenwelt.de", "timestamp": "2018-11-07T14:55:21.354378", "browser": "chrome", "browser-platform": "windows", "browser-version": "70.0.3538.77"}
{"method": "GET", "path": "/dashboards/_render_async_sql_query/b2287c46-c5e6-4479-ab50-5269adc62ec7", "endpoint": "dashboards.render_async_sql_query", "view-args": {"id": "b2287c46-c5e6-4479-ab50-5269adc62ec7"}, "status": 200, "user": "felix.pittorf@lampenwelt.de", "timestamp": "2018-11-07T14:55:21.366617", "browser": "chrome", "browser-platform": "windows", "browser-version": "70.0.3538.77"}
{"method": "GET", "path": "/dashboards/_render_async_sql_query/bf74e53b-f6f7-4d4d-8856-381d09c2eba4", "endpoint": "dashboards.render_async_sql_query", "view-args": {"id": "bf74e53b-f6f7-4d4d-8856-381d09c2eba4"}, "status": 200, "user": "felix.pittorf@lampenwelt.de", "timestamp": "2018-11-07T14:55:21.475647", "browser": "chrome", "browser-platform": "windows", "browser-version": "70.0.3538.77"}
{"method": "GET", "path": "/dashboards/_render_async_sql_query/f7fd16a8-25bd-407d-a53a-521aad50c047", "endpoint": "dashboards.render_async_sql_query", "view-args": {"id": "f7fd16a8-25bd-407d-a53a-521aad50c047"}, "status": 200, "user": "felix.pittorf@lampenwelt.de", "timestamp": "2018-11-07T14:55:21.524964", "browser": "chrome", "browser-platform": "windows", "browser-version": "70.0.3538.77"}
{"method": "GET", "path": "/dashboards/_render_async_sql_query/ec5a601e-5f2d-4e1c-a98f-497db815e1bb", "endpoint": "dashboards.render_async_sql_query", "view-args": {"id": "ec5a601e-5f2d-4e1c-a98f-497db815e1bb"}, "status": 200, "user": "felix.pittorf@lampenwelt.de", "timestamp": "2018-11-07T14:55:21.566278", "browser": "chrome", "browser-platform": "windows", "browser-version": "70.0.3538.77"}
{"method": "GET", "path": "/dashboards/_render_async_sql_query/3136e63d-f088-450d-9e36-342ae4a36f60", "endpoint": "dashboards.render_async_sql_query", "view-args": {"id": "3136e63d-f088-450d-9e36-342ae4a36f60"}, "status": 200, "user": "felix.pittorf@lampenwelt.de", "timestamp": "2018-11-07T14:55:21.587669", "browser": "chrome", "browser-platform": "windows", "browser-version": "70.0.3538.77"}
{"method": "GET", "path": "/dashboards/_render_async_sql_query/f5172d66-508e-4c85-87c7-e237af49f20b", "endpoint": "dashboards.render_async_sql_query", "view-args": {"id": "f5172d66-508e-4c85-87c7-e237af49f20b"}, "status": 200, "user": "felix.pittorf@lampenwelt.de", "timestamp": "2018-11-07T14:55:21.626935", "browser": "chrome", "browser-platform": "windows", "browser-version": "70.0.3538.77"}
{"method": "GET", "path": "/dashboards/_render_async_sql_query/f11d9d67-571a-409d-8cbc-f6bee8becd71", "endpoint": "dashboards.render_async_sql_query", "view-args": {"id": "f11d9d67-571a-409d-8cbc-f6bee8becd71"}, "status": 200, "user": "felix.pittorf@lampenwelt.de", "timestamp": "2018-11-07T14:55:21.633485", "browser": "chrome", "browser-platform": "windows", "browser-version": "70.0.3538.77"}
{"method": "GET", "path": "/dashboards/_render_async_sql_query/e319f7b3-3410-4dfa-81cf-ad9690c3372a", "endpoint": "dashboards.render_async_sql_query", "view-args": {"id": "e319f7b3-3410-4dfa-81cf-ad9690c3372a"}, "status": 200, "user": "felix.pittorf@lampenwelt.de", "timestamp": "2018-11-07T14:55:21.651163", "browser": "chrome", "browser-platform": "windows", "browser-version": "70.0.3538.77"}
{"method": "GET", "path": "/dashboards/_render_async_sql_query/25b68242-24bb-4d9f-b8e2-07525589707e", "endpoint": "dashboards.render_async_sql_query", "view-args": {"id": "25b68242-24bb-4d9f-b8e2-07525589707e"}, "status": 200, "user": "felix.pittorf@lampenwelt.de", "timestamp": "2018-11-07T14:55:21.686456", "browser": "chrome", "browser-platform": "windows", "browser-version": "70.0.3538.77"}
{"method": "GET", "path": "/dashboards/_render_async_sql_query/ca7fce56-46eb-45ec-b8f3-c78588256bc2", "endpoint": "dashboards.render_async_sql_query", "view-args": {"id": "ca7fce56-46eb-45ec-b8f3-c78588256bc2"}, "status": 200, "user": "felix.pittorf@lampenwelt.de", "timestamp": "2018-11-07T14:55:21.705342", "browser": "chrome", "browser-platform": "windows", "browser-version": "70.0.3538.77"}
{"method": "GET", "path": "/dashboards/_render_async_sql_query/d1eebc27-2738-45cf-a0b8-2723232cae83", "endpoint": "dashboards.render_async_sql_query", "view-args": {"id": "d1eebc27-2738-45cf-a0b8-2723232cae83"}, "status": 200, "user": "felix.pittorf@lampenwelt.de", "timestamp": "2018-11-07T14:55:21.720060", "browser": "chrome", "browser-platform": "windows", "browser-version": "70.0.3538.77"}
{"method": "GET", "path": "/dashboards/_auto-complete/shop_dim.webshop_performance_fact/is_mobile/", "endpoint": "dashboards.auto_complete", "view-args": {"table_name": "shop_dim.webshop_performance_fact", "column_name": "is_mobile"}, "status": 200, "user": "felix.pittorf@lampenwelt.de", "timestamp": "2018-11-07T14:55:23.918799", "browser": "chrome", "browser-platform": "windows", "browser-version": "70.0.3538.77"}
{"method": "POST", "path": "/dashboards/shop-performance-overview", "endpoint": "dashboards.view_dashboard", "view-args": {"id": "shop-performance-overview"}, "status": 200, "user": "felix.pittorf@lampenwelt.de", "timestamp": "2018-11-07T14:55:27.084218", "browser": "chrome", "browser-platform": "windows", "browser-version": "70.0.3538.77"}
{"method": "GET", "path": "/dashboards/_render_async_sql_query/6361c4c9-2bec-4aca-8099-95e3f5b94311", "endpoint": "dashboards.render_async_sql_query", "view-args": {"id": "6361c4c9-2bec-4aca-8099-95e3f5b94311"}, "status": 200, "user": "felix.pittorf@lampenwelt.de", "timestamp": "2018-11-07T14:55:27.569990", "browser": "chrome", "browser-platform": "windows", "browser-version": "70.0.3538.77"}
{"method": "GET", "path": "/dashboards/_render_async_sql_query/e8a9e61c-067c-4740-b26b-3b9ecb428cbd", "endpoint": "dashboards.render_async_sql_query", "view-args": {"id": "e8a9e61c-067c-4740-b26b-3b9ecb428cbd"}, "status": 200, "user": "felix.pittorf@lampenwelt.de", "timestamp": "2018-11-07T14:55:27.571957", "browser": "chrome", "browser-platform": "windows", "browser-version": "70.0.3538.77"}
{"method": "GET", "path": "/dashboards/_render_async_sql_query/c6e15f5b-5631-43ea-9072-e22c9119a021", "endpoint": "dashboards.render_async_sql_query", "view-args": {"id": "c6e15f5b-5631-43ea-9072-e22c9119a021"}, "status": 200, "user": "felix.pittorf@lampenwelt.de", "timestamp": "2018-11-07T14:55:27.581083", "browser": "chrome", "browser-platform": "windows", "browser-version": "70.0.3538.77"}
{"method": "GET", "path": "/dashboards/_last_successful_import", "endpoint": "dashboards.last_successful_import", "view-args": {}, "status": 200, "user": "felix.pittorf@lampenwelt.de", "timestamp": "2018-11-07T14:55:27.589434", "browser": "chrome", "browser-platform": "windows", "browser-version": "70.0.3538.77"}
{"method": "GET", "path": "/dashboards/_render_async_sql_query/12bee2ae-c844-448e-beac-cf0549e28e95", "endpoint": "dashboards.render_async_sql_query", "view-args": {"id": "12bee2ae-c844-448e-beac-cf0549e28e95"}, "status": 200, "user": "felix.pittorf@lampenwelt.de", "timestamp": "2018-11-07T14:55:27.597668", "browser": "chrome", "browser-platform": "windows", "browser-version": "70.0.3538.77"}
{"method": "GET", "path": "/dashboards/_render_async_sql_query/d4d54724-fc5d-4a1f-bf3e-fbb42fc68d50", "endpoint": "dashboards.render_async_sql_query", "view-args": {"id": "d4d54724-fc5d-4a1f-bf3e-fbb42fc68d50"}, "status": 200, "user": "felix.pittorf@lampenwelt.de", "timestamp": "2018-11-07T14:55:27.687580", "browser": "chrome", "browser-platform": "windows", "browser-version": "70.0.3538.77"}
{"method": "GET", "path": "/dashboards/_render_async_sql_query/cc458ac7-d9a3-41e8-87c7-6e15e04f954d", "endpoint": "dashboards.render_async_sql_query", "view-args": {"id": "cc458ac7-d9a3-41e8-87c7-6e15e04f954d"}, "status": 200, "user": "felix.pittorf@lampenwelt.de", "timestamp": "2018-11-07T14:55:27.687814", "browser": "chrome", "browser-platform": "windows", "browser-version": "70.0.3538.77"}
{"method": "GET", "path": "/dashboards/_render_async_sql_query/3ae14234-e55e-45f5-9681-2255dd894150", "endpoint": "dashboards.render_async_sql_query", "view-args": {"id": "3ae14234-e55e-45f5-9681-2255dd894150"}, "status": 200, "user": "felix.pittorf@lampenwelt.de", "timestamp": "2018-11-07T14:55:27.702459", "browser": "chrome", "browser-platform": "windows", "browser-version": "70.0.3538.77"}
{"method": "GET", "path": "/dashboards/_render_async_sql_query/fe4471d8-f62d-4ecf-af23-fdc87db944ab", "endpoint": "dashboards.render_async_sql_query", "view-args": {"id": "fe4471d8-f62d-4ecf-af23-fdc87db944ab"}, "status": 200, "user": "felix.pittorf@lampenwelt.de", "timestamp": "2018-11-07T14:55:27.714489", "browser": "chrome", "browser-platform": "windows", "browser-version": "70.0.3538.77"}
{"method": "GET", "path": "/dashboards/_render_async_sql_query/d3f4b216-d611-483d-b1a2-50616ed605f1", "endpoint": "dashboards.render_async_sql_query", "view-args": {"id": "d3f4b216-d611-483d-b1a2-50616ed605f1"}, "status": 200, "user": "felix.pittorf@lampenwelt.de", "timestamp": "2018-11-07T14:55:27.758660", "browser": "chrome", "browser-platform": "windows", "browser-version": "70.0.3538.77"}
{"method": "GET", "path": "/dashboards/_render_async_sql_query/1dc6d226-50c0-4320-a3c4-d62ab502ccdb", "endpoint": "dashboards.render_async_sql_query", "view-args": {"id": "1dc6d226-50c0-4320-a3c4-d62ab502ccdb"}, "status": 200, "user": "felix.pittorf@lampenwelt.de", "timestamp": "2018-11-07T14:55:27.761907", "browser": "chrome", "browser-platform": "windows", "browser-version": "70.0.3538.77"}
{"method": "GET", "path": "/dashboards/_render_async_sql_query/39d517d6-b6f5-4890-b515-efd5414d9850", "endpoint": "dashboards.render_async_sql_query", "view-args": {"id": "39d517d6-b6f5-4890-b515-efd5414d9850"}, "status": 200, "user": "felix.pittorf@lampenwelt.de", "timestamp": "2018-11-07T14:55:27.764597", "browser": "chrome", "browser-platform": "windows", "browser-version": "70.0.3538.77"}
{"method": "GET", "path": "/dashboards/_render_async_sql_query/d9bbbbfb-4c7c-4e58-b5fa-2a32a9d3fd45", "endpoint": "dashboards.render_async_sql_query", "view-args": {"id": "d9bbbbfb-4c7c-4e58-b5fa-2a32a9d3fd45"}, "status": 200, "user": "felix.pittorf@lampenwelt.de", "timestamp": "2018-11-07T14:55:27.847083", "browser": "chrome", "browser-platform": "windows", "browser-version": "70.0.3538.77"}
{"method": "GET", "path": "/dashboards/_render_async_sql_query/01c0543f-cc8e-4404-ad13-8fd3c05eb3f8", "endpoint": "dashboards.render_async_sql_query", "view-args": {"id": "01c0543f-cc8e-4404-ad13-8fd3c05eb3f8"}, "status": 200, "user": "felix.pittorf@lampenwelt.de", "timestamp": "2018-11-07T14:55:27.856270", "browser": "chrome", "browser-platform": "windows", "browser-version": "70.0.3538.77"}
{"method": "GET", "path": "/dashboards/_render_async_sql_query/8399532e-2d91-4740-9cd7-bb8f515c5b08", "endpoint": "dashboards.render_async_sql_query", "view-args": {"id": "8399532e-2d91-4740-9cd7-bb8f515c5b08"}, "status": 200, "user": "felix.pittorf@lampenwelt.de", "timestamp": "2018-11-07T14:55:27.901915", "browser": "chrome", "browser-platform": "windows", "browser-version": "70.0.3538.77"}
{"method": "GET", "path": "/dashboards/_render_async_sql_query/27e9c2c4-83bc-47c3-a800-85d0b4da6985", "endpoint": "dashboards.render_async_sql_query", "view-args": {"id": "27e9c2c4-83bc-47c3-a800-85d0b4da6985"}, "status": 200, "user": "felix.pittorf@lampenwelt.de", "timestamp": "2018-11-07T14:55:27.911283", "browser": "chrome", "browser-platform": "windows", "browser-version": "70.0.3538.77"}
{"method": "GET", "path": "/dashboards/_render_async_sql_query/473c30ab-dfbf-4797-a48f-157c77ee2320", "endpoint": "dashboards.render_async_sql_query", "view-args": {"id": "473c30ab-dfbf-4797-a48f-157c77ee2320"}, "status": 200, "user": "felix.pittorf@lampenwelt.de", "timestamp": "2018-11-07T14:55:28.185963", "browser": "chrome", "browser-platform": "windows", "browser-version": "70.0.3538.77"}
{"method": "GET", "path": "/dashboards/_render_async_sql_query/486c200c-b5b2-488f-beea-ceab1db167ad", "endpoint": "dashboards.render_async_sql_query", "view-args": {"id": "486c200c-b5b2-488f-beea-ceab1db167ad"}, "status": 200, "user": "felix.pittorf@lampenwelt.de", "timestamp": "2018-11-07T14:55:28.195625", "browser": "chrome", "browser-platform": "windows", "browser-version": "70.0.3538.77"}
{"method": "GET", "path": "/dashboards/_render_async_sql_query/9bc1b937-04f2-4ca9-9b3c-e4fb7f490f28", "endpoint": "dashboards.render_async_sql_query", "view-args": {"id": "9bc1b937-04f2-4ca9-9b3c-e4fb7f490f28"}, "status": 200, "user": "felix.pittorf@lampenwelt.de", "timestamp": "2018-11-07T14:55:28.203258", "browser": "chrome", "browser-platform": "windows", "browser-version": "70.0.3538.77"}
{"method": "GET", "path": "/dashboards/_render_async_sql_query/c3058cec-e587-4fe9-b2b3-011404647934", "endpoint": "dashboards.render_async_sql_query", "view-args": {"id": "c3058cec-e587-4fe9-b2b3-011404647934"}, "status": 200, "user": "felix.pittorf@lampenwelt.de", "timestamp": "2018-11-07T14:55:28.257726", "browser": "chrome", "browser-platform": "windows", "browser-version": "70.0.3538.77"}
{"method": "GET", "path": "/dashboards/_render_async_sql_query/4e03d915-9623-472d-b317-1203093eb76c", "endpoint": "dashboards.render_async_sql_query", "view-args": {"id": "4e03d915-9623-472d-b317-1203093eb76c"}, "status": 200, "user": "felix.pittorf@lampenwelt.de", "timestamp": "2018-11-07T14:55:28.295348", "browser": "chrome", "browser-platform": "windows", "browser-version": "70.0.3538.77"}
